setup.py
sunnyday/__init__.py
sunnyday/sunnyday.py
twelve_hour_weather.egg-info/PKG-INFO
twelve_hour_weather.egg-info/SOURCES.txt
twelve_hour_weather.egg-info/dependency_links.txt
twelve_hour_weather.egg-info/requires.txt
twelve_hour_weather.egg-info/top_level.txt